<?xml version="1.0"?>
<CCO path="c:\datacap\ssnit\fingerprint\640.cco">
	<L l="4459" t="295" b="380" r="4792" i="1"><W l="4459" t="295" r="4792" b="380" x="1" y="6">SS-M3</W>
	</L><L l="1957" t="495" b="562" r="2910" i="2"><W l="1957" t="497" r="2167" b="550" x="1" y="1">Social</W>
		<W l="2195" t="495" r="2479" b="562" x="2" y="1">Security</W>
		<W l="2507" t="495" r="2772" b="550" x="3" y="1">No./Ref.</W>
		<W l="2802" t="497" r="2910" b="549" x="4" y="1">No.</W>
	</L><L l="2277" t="745" b="795" r="3015" i="3"><W l="2277" t="745" r="2620" b="795" x="1" y="2">REPUBLIC</W>
		<W l="2652" t="745" r="2739" b="795" x="2" y="2">0:-</W>
		<W l="2727" t="765" r="2735" b="772" x="1" y="3">•</W>
		<W l="2769" t="745" r="3015" b="795" x="2" y="3">GHANA</W>
	</L><L l="1715" t="874" b="927" r="3592" i="4"><W l="1715" t="875" r="1974" b="927" x="1" y="4">SOCIAL</W>
		<W l="2000" t="875" r="2357" b="927" x="2" y="4">SECURITY</W>
		<W l="2375" t="875" r="2520" b="927" x="3" y="4">AND</W>
		<W l="2552" t="875" r="2892" b="925" x="4" y="4">NATIONAL</W>
		<W l="2922" t="875" r="3330" b="927" x="5" y="4">INSURANCE</W>
		<W l="3357" t="874" r="3592" b="925" x="6" y="4">TRUST</W>
	</L><L l="1800" t="1004" b="1064" r="3492" i="5"><W l="1800" t="1004" r="2867" b="1064" x="1" y="5">NOMINEES/BENEFICIARIES</W>
		<W l="2904" t="1004" r="3232" b="1062" x="2" y="5">DETAILS</W>
		<W l="3269" t="1004" r="3492" b="1062" x="3" y="5">FORM</W>
	</L><L l="1349" t="1202" b="1267" r="4112" i="6"><W l="1349" t="1205" r="1425" b="1255" x="1" y="7">All</W>
		<W l="1455" t="1204" r="1729" b="1255" x="2" y="7">Sections</W>
		<W l="1759" t="1207" r="1910" b="1255" x="3" y="7">must</W>
		<W l="1939" t="1205" r="2010" b="1255" x="4" y="7">be</W>
		<W l="2039" t="1204" r="2364" b="1267" x="5" y="7">completed</W>
		<W l="2395" t="1204" r="2442" b="1254" x="6" y="7">in</W>
		<W l="2475" t="1202" r="2700" b="1254" x="7" y="7">BLACK</W>
		<W l="2725" t="1217" r="2785" b="1254" x="8" y="7">or</W>
		<W l="2814" t="1204" r="2989" b="1254" x="9" y="7">BLUE</W>
		<W l="3020" t="1204" r="3132" b="1254" x="10" y="7">INK</W>
		<W l="3160" t="1205" r="3270" b="1255" x="11" y="7">and</W>
		<W l="3302" t="1204" r="3349" b="1254" x="12" y="7">in</W>
		<W l="3382" t="1202" r="3617" b="1252" x="13" y="7">BLOCK</W>
		<W l="3645" t="1202" r="3955" b="1254" x="14" y="7">LETTERS</W>
		<W l="3985" t="1204" r="4112" b="1267" x="15" y="7">only</W>
	</L><L l="372" t="1352" b="1419" r="4065" i="7"><W l="372" t="1362" r="562" b="1415" x="1" y="8">TYPE</W>
		<W l="594" t="1362" r="689" b="1415" x="2" y="8">OF</W>
		<W l="722" t="1360" r="1182" b="1415" x="3" y="8">NOMINATION</W>
		<W l="1352" t="1354" r="1502" b="1417" x="1" y="13">(Tick</W>
		<W l="1529" t="1369" r="1554" b="1405" x="2" y="13">-N</W>
		<W l="1590" t="1355" r="1717" b="1419" x="3" y="13">only</W>
		<W l="1744" t="1355" r="1902" b="1417" x="4" y="13">one)</W>
		<W l="2352" t="1352" r="2507" b="1404" x="1" y="15">Initial</W>
		<W l="2537" t="1352" r="2877" b="1405" x="2" y="15">Nomination</W>
		<W l="3360" t="1352" r="3602" b="1417" x="1" y="17">Change</W>
		<W l="3630" t="1352" r="3690" b="1405" x="2" y="17">of</W>
		<W l="3715" t="1352" r="4065" b="1405" x="3" y="17">Nomination</W>
	</L><L l="375" t="1515" b="1567" r="665" i="8"><W l="375" t="1515" r="665" b="1567" x="1" y="9">Surname</W>
	</L><L l="377" t="1645" b="1695" r="725" i="9"><W l="377" t="1645" r="515" b="1695" x="1" y="10">First</W>
		<W l="545" t="1645" r="725" b="1695" x="2" y="10">Name</W>
	</L><L l="377" t="1774" b="1835" r="852" i="10"><W l="377" t="1774" r="557" b="1825" x="1" y="11">°tier</W>
		<W l="587" t="1774" r="852" b="1835" x="2" y="11">Names)</W>
	</L><L l="375" t="1905" b="1962" r="3672" i="11"><W l="375" t="1907" r="555" b="1960" x="1" y="12">Family</W>
		<W l="575" t="1905" r="775" b="1960" x="2" y="12">System</W>
		<W l="797" t="1905" r="852" b="1949" x="3" y="12">of</W>
		<W l="870" t="1905" r="1170" b="1949" x="4" y="12">Inheritance</W>
		<W l="1505" t="1910" r="1765" b="1962" x="1" y="14">Paternal</W>
		<W l="2520" t="1910" r="2782" b="1960" x="1" y="16">Maternal</W>
		<W l="3534" t="1910" r="3672" b="1959" x="1" y="18">Dual</W>
	</L><L l="897" t="2097" b="2159" r="4102" i="12"><W l="897" t="2102" r="905" b="2147" x="1" y="19">I</W>
		<W l="932" t="2100" r="1120" b="2159" x="2" y="19">hereby</W>
		<W l="1142" t="2100" r="1347" b="2147" x="3" y="19">declare</W>
		<W l="1369" t="2100" r="1475" b="2147" x="4" y="19">that</W>
		<W l="1494" t="2100" r="1582" b="2147" x="5" y="19">the</W>
		<W l="1605" t="2100" r="1870" b="2159" x="6" y="19">person(s)</W>
		<W l="1897" t="2099" r="2189" b="2147" x="7" y="19">mentioned</W>
		<W l="2215" t="2099" r="2375" b="2145" x="8" y="19">below</W>
		<W l="2397" t="2110" r="2485" b="2147" x="9" y="19">are</W>
		<W l="2507" t="2100" r="2557" b="2145" x="10" y="19">to</W>
		<W l="2582" t="2099" r="2780" b="2145" x="11" y="19">receive</W>
		<W l="2804" t="2110" r="2902" b="2157" x="12" y="19">any</W>
		<W l="2927" t="2097" r="3150" b="2147" x="13" y="19">Benefits</W>
		<W l="3174" t="2099" r="3275" b="2145" x="14" y="19">due</W>
		<W l="3300" t="2110" r="3384" b="2145" x="15" y="19">me</W>
		<W l="3407" t="2097" r="3449" b="2145" x="16" y="19">in</W>
		<W l="3472" t="2097" r="3560" b="2145" x="17" y="19">the</W>
		<W l="3582" t="2099" r="3737" b="2145" x="18" y="19">event</W>
		<W l="3757" t="2097" r="3812" b="2145" x="19" y="19">of</W>
		<W l="3832" t="2110" r="3910" b="2157" x="20" y="19">my</W>
		<W l="3932" t="2097" r="4102" b="2145" x="21" y="19">death.</W>
	</L><L l="369" t="2237" b="2297" r="1187" i="13"><W l="369" t="2237" r="1097" b="2287" x="1" y="20">NOMINEE/BENEFICIARY</W>
		<W l="1115" t="2237" r="1187" b="2297" x="2" y="20">(1)</W>
	</L><L l="377" t="2352" b="2402" r="667" i="14"><W l="377" t="2352" r="667" b="2402" x="1" y="21">Surname</W>
	</L><L l="379" t="2477" b="2527" r="725" i="15"><W l="379" t="2477" r="515" b="2527" x="1" y="22">First</W>
		<W l="545" t="2477" r="725" b="2527" x="2" y="22">Name</W>
	</L><L l="377" t="2602" b="2665" r="847" i="16"><W l="377" t="2602" r="557" b="2652" x="1" y="23">Other</W>
		<W l="587" t="2602" r="847" b="2665" x="2" y="23">Name(s;</W>
	</L><L l="379" t="2739" b="2795" r="4720" i="17"><W l="379" t="2744" r="520" b="2792" x="1" y="24">Date</W>
		<W l="550" t="2742" r="607" b="2792" x="2" y="24">of</W>
		<W l="634" t="2742" r="769" b="2792" x="3" y="24">Birth</W>
		<W l="3462" t="2739" r="3839" b="2790" x="1" y="37">Gender/Sex</W>
		<W l="4097" t="2745" r="4237" b="2795" x="1" y="38">Male</W>
		<W l="4490" t="2744" r="4720" b="2794" x="1" y="39">Female</W>
	</L><L l="380" t="2887" b="2950" r="1455" i="18"><W l="380" t="2889" r="769" b="2939" x="1" y="25">Relationsiio</W>
		<W l="800" t="2887" r="937" b="2950" x="2" y="25">(The</W>
		<W l="967" t="2887" r="1242" b="2939" x="3" y="25">Nominee</W>
		<W l="1272" t="2887" r="1317" b="2937" x="4" y="25">is</W>
		<W l="1345" t="2887" r="1455" b="2950" x="5" y="25">my)</W>
	</L><L l="380" t="3017" b="3069" r="1099" i="19"><W l="380" t="3017" r="432" b="3069" x="1" y="26">%</W>
		<W l="462" t="3017" r="520" b="3069" x="2" y="26">of</W>
		<W l="545" t="3017" r="795" b="3069" x="3" y="26">Benefits</W>
		<W l="824" t="3017" r="1099" b="3067" x="4" y="26">allocated</W>
	</L><L l="382" t="3157" b="3227" r="3229" i="20"><W l="382" t="3162" r="442" b="3210" x="1" y="27">ID</W>
		<W l="470" t="3162" r="620" b="3224" x="2" y="27">Type</W>
		<W l="797" t="3165" r="900" b="3214" x="3" y="27">NIA</W>
		<W l="1035" t="3165" r="1272" b="3215" x="4" y="27">Driver's</W>
		<W l="1302" t="3164" r="1544" b="3215" x="5" y="27">License</W>
		<W l="1685" t="3164" r="1972" b="3227" x="6" y="27">Passport</W>
		<W l="2107" t="3162" r="2262" b="3212" x="7" y="27">NHIS</W>
		<W l="2397" t="3162" r="2615" b="3212" x="8" y="27">Voter's</W>
		<W l="3025" t="3159" r="3085" b="3207" x="1" y="33">ID</W>
		<W l="3115" t="3157" r="3229" b="3207" x="2" y="33">NO.</W>
	</L><L l="382" t="3305" b="3369" r="2345" i="21"><W l="382" t="3310" r="867" b="3362" x="1" y="28">RESIDENTIAL</W>
		<W l="889" t="3307" r="1644" b="3360" x="2" y="28">ADDRESS/LOCATION</W>
		<W l="1740" t="3307" r="1845" b="3369" x="3" y="28">(Do</W>
		<W l="1877" t="3307" r="1970" b="3357" x="4" y="28">not</W>
		<W l="1995" t="3305" r="2345" b="3367" x="5" y="28">abbreviate)</W>
	</L><L l="382" t="3450" b="3502" r="3115" i="22"><W l="382" t="3454" r="580" b="3502" x="1" y="29">House</W>
		<W l="614" t="3454" r="860" b="3502" x="2" y="29">Number</W>
		<W l="2705" t="3450" r="2902" b="3500" x="1" y="34">House</W>
		<W l="2934" t="3450" r="3115" b="3502" x="2" y="34">Name</W>
	</L><L l="380" t="3575" b="3629" r="2925" i="23"><W l="380" t="3580" r="572" b="3629" x="1" y="30">Street</W>
		<W l="602" t="3580" r="780" b="3627" x="2" y="30">Name</W>
		<W l="2702" t="3575" r="2925" b="3625" x="1" y="35">Suburb</W>
	</L><L l="379" t="3705" b="3772" r="2924" i="24"><W l="379" t="3707" r="697" b="3772" x="1" y="31">Town/City</W>
		<W l="2715" t="3705" r="2924" b="3769" x="1" y="36">Region</W>
	</L><L l="380" t="3844" b="3910" r="2682" i="25"><W l="380" t="3849" r="717" b="3902" x="1" y="32">Landmark</W>
		<W l="824" t="3847" r="957" b="3910" x="2" y="32">(e.g.</W>
		<W l="997" t="3845" r="1444" b="3909" x="3" y="32">Vear/Opposite</W>
		<W l="1474" t="3857" r="1505" b="3895" x="4" y="32">a</W>
		<W l="1535" t="3844" r="2520" b="3907" x="5" y="32">School/Church/Palace/Mosque</W>
		<W l="2549" t="3845" r="2682" b="3907" x="6" y="32">etc.)</W>
	</L><L l="374" t="4192" b="4254" r="1195" i="26"><W l="374" t="4192" r="1102" b="4244" x="1" y="40">NOMINEE/BENEFICIARY</W>
		<W l="1120" t="4192" r="1195" b="4254" x="2" y="40">(2)</W>
	</L><L l="384" t="4360" b="4410" r="672" i="27"><W l="384" t="4360" r="672" b="4410" x="1" y="41">Surname</W>
	</L><L l="387" t="4485" b="4535" r="732" i="28"><W l="387" t="4485" r="522" b="4535" x="1" y="42">7-irst</W>
		<W l="552" t="4485" r="732" b="4535" x="2" y="42">Name</W>
	</L><L l="382" t="4610" b="4670" r="859" i="29"><W l="382" t="4610" r="562" b="4660" x="1" y="43">Other</W>
		<W l="592" t="4610" r="859" b="4670" x="2" y="43">Names)</W>
	</L><L l="384" t="4742" b="4802" r="4725" i="30"><W l="384" t="4750" r="525" b="4800" x="1" y="44">Date</W>
		<W l="555" t="4762" r="585" b="4799" x="2" y="44">o</W>
		<W l="640" t="4749" r="774" b="4799" x="3" y="44">Birti</W>
		<W l="3467" t="4742" r="3844" b="4795" x="1" y="57">Gencer/Sex</W>
		<W l="4102" t="4752" r="4242" b="4802" x="1" y="58">Male</W>
		<W l="4495" t="4750" r="4725" b="4802" x="1" y="59">Female</W>
	</L><L l="384" t="4892" b="4955" r="1460" i="31"><W l="384" t="4894" r="774" b="4955" x="1" y="45">Relationship</W>
		<W l="805" t="4894" r="942" b="4955" x="2" y="45">(The</W>
		<W l="972" t="4892" r="1247" b="4944" x="3" y="45">Nominee</W>
		<W l="1277" t="4892" r="1322" b="4942" x="4" y="45">is</W>
		<W l="1350" t="4892" r="1460" b="4955" x="5" y="45">my)</W>
	</L><L l="384" t="5022" b="5075" r="1102" i="32"><W l="384" t="5024" r="437" b="5075" x="1" y="46">%</W>
		<W l="467" t="5024" r="525" b="5074" x="2" y="46">of</W>
		<W l="550" t="5022" r="800" b="5074" x="3" y="46">Benelts</W>
		<W l="827" t="5022" r="1102" b="5072" x="4" y="46">allocated</W>
	</L><L l="387" t="5160" b="5232" r="3234" i="33"><W l="387" t="5169" r="449" b="5219" x="1" y="47">ID</W>
		<W l="475" t="5169" r="627" b="5232" x="2" y="47">Type</W>
		<W l="802" t="5172" r="905" b="5224" x="3" y="47">NIA</W>
		<W l="1040" t="5170" r="1277" b="5222" x="4" y="47">Driver's</W>
		<W l="1307" t="5170" r="1549" b="5222" x="5" y="47">License</W>
		<W l="1690" t="5170" r="1977" b="5232" x="6" y="47">Passport</W>
		<W l="2112" t="5167" r="2267" b="5220" x="7" y="47">NHIS</W>
		<W l="2402" t="5167" r="2620" b="5219" x="8" y="47">Voter's</W>
		<W l="3030" t="5160" r="3090" b="5210" x="1" y="53">ID</W>
		<W l="3120" t="5160" r="3234" b="5212" x="2" y="53">NO.</W>
	</L><L l="387" t="5312" b="5377" r="2350" i="34"><W l="387" t="5320" r="872" b="5372" x="1" y="48">RESIDENTIAL</W>
		<W l="894" t="5315" r="1649" b="5370" x="2" y="48">ADDRESS/LOCATION</W>
		<W l="1745" t="5315" r="1850" b="5377" x="3" y="48">(Do</W>
		<W l="1882" t="5315" r="1975" b="5365" x="4" y="48">not</W>
		<W l="2002" t="5312" r="2350" b="5375" x="5" y="48">abbreviate)</W>
	</L><L l="387" t="5455" b="5515" r="3119" i="35"><W l="387" t="5465" r="587" b="5515" x="1" y="49">House</W>
		<W l="620" t="5464" r="650" b="5514" x="2" y="49">I\</W>
		<W l="670" t="5475" r="865" b="5514" x="3" y="49">umoer</W>
		<W l="2710" t="5455" r="2907" b="5505" x="1" y="54">House</W>
		<W l="2939" t="5455" r="3119" b="5505" x="2" y="54">Name</W>
	</L><L l="385" t="5579" b="5640" r="2930" i="36"><W l="385" t="5589" r="577" b="5640" x="1" y="50">Street</W>
		<W l="607" t="5589" r="785" b="5637" x="2" y="50">Name</W>
		<W l="2707" t="5579" r="2930" b="5630" x="1" y="55">Suburb</W>
	</L><L l="385" t="5710" b="5782" r="2930" i="37"><W l="385" t="5719" r="702" b="5782" x="1" y="51">Town/City</W>
		<W l="2715" t="5710" r="2930" b="5772" x="1" y="56">Region</W>
	</L><L l="385" t="5849" b="5920" r="2689" i="38"><W l="385" t="5857" r="722" b="5910" x="1" y="52">Landmark</W>
		<W l="830" t="5857" r="962" b="5920" x="2" y="52">(e.g.</W>
		<W l="995" t="5854" r="1450" b="5915" x="3" y="52">Near/Opposite</W>
		<W l="1479" t="5865" r="1510" b="5904" x="4" y="52">a</W>
		<W l="1540" t="5850" r="2527" b="5910" x="5" y="52">SchoolCiurch/Palace/Mosque</W>
		<W l="2555" t="5849" r="2689" b="5910" x="6" y="52">etc.)</W>
	</L><L l="2454" t="6355" b="6410" r="4907" i="39"><W l="2454" t="6355" r="2585" b="6410" x="1" y="60">Page</W>
		<W l="2612" t="6355" r="2627" b="6400" x="2" y="60">1</W>
		<W l="2657" t="6355" r="2707" b="6400" x="3" y="60">of</W>
		<W l="2722" t="6355" r="2750" b="6397" x="4" y="60">2</W>
		<W l="4457" t="6355" r="4599" b="6395" x="5" y="60">FORM</W>
		<W l="4622" t="6355" r="4907" b="6395" x="6" y="60">SS-M312013</W>
	</L></CCO>
